axtended_key/__init__.py
axtended_key/main.py
axtended_key/models/__init__.py
axtended_key/models/certificate_metadata.py
axtended_key/models/certificate_paths.py
axtended_key/services/__init__.py
axtended_key/services/certificate_manager.py
axtended_key/services/keychain_manager.py
axtended_key/utils/logger.py
axtended_key/utils/openssl_verification.py
axtendedkey-0.1.4.dist-info/LICENSE
axtendedkey-0.1.4.dist-info/METADATA
axtendedkey-0.1.4.dist-info/WHEEL
axtendedkey-0.1.4.dist-info/entry_points.txt
axtendedkey-0.1.4.dist-info/RECORD
