Metadata-Version: 2.1
Name: AxtendedKey
Version: 0.1.4
Summary: Easy AX Permissions for Xcode Builds
Home-page: https://github.com/zschuessler/AXtendedKey
License: Unlicense
Author: Zachary Schuessler
Author-email: zlschuessler@gmail.com
Requires-Python: >=3.9
Classifier: License :: OSI Approved
Classifier: Programming Language :: Python :: 3
Classifier: Programming Language :: Python :: 3.9
Classifier: Programming Language :: Python :: 3.10
Classifier: Programming Language :: Python :: 3.11
Classifier: Programming Language :: Python :: 3.12
Classifier: Programming Language :: Python :: 3.13
Requires-Dist: click (>=8.1.7,<9.0.0)
Project-URL: Repository, https://github.com/zschuessler/AXtendedKey
